intezer_analyze_cli/__init__.py
intezer_analyze_cli/cli.py
intezer_analyze_cli/commands.py
intezer_analyze_cli/config.py
intezer_analyze_cli/key_store.py
intezer_analyze_cli/utilities.py
intezer_analyze_cli-1.12.0.dist-info/licenses/LICENSE
intezer_analyze_cli-1.12.0.dist-info/METADATA
intezer_analyze_cli-1.12.0.dist-info/WHEEL
intezer_analyze_cli-1.12.0.dist-info/entry_points.txt
intezer_analyze_cli-1.12.0.dist-info/top_level.txt
intezer_analyze_cli-1.12.0.dist-info/RECORD
