Metadata-Version: 2.4
Name: intezer-analyze-cli
Version: 1.12.0
Summary: Client library for Intezer cloud service
Author: Intezer Labs ltd.
License: Apache License v2
Keywords: intezer
Classifier: Programming Language :: Python :: 3.8
Classifier: Programming Language :: Python :: 3.9
Classifier: Programming Language :: Python :: 3.10
Classifier: Programming Language :: Python :: 3.11
Classifier: Programming Language :: Python :: 3.12
Requires-Python: >=3.8
License-File: LICENSE
Requires-Dist: click==7.1.2
Requires-Dist: intezer-sdk<2,>=1.15.2
Dynamic: author
Dynamic: classifier
Dynamic: description
Dynamic: description-content-type
Dynamic: keywords
Dynamic: license
Dynamic: license-file
Dynamic: requires-dist
Dynamic: requires-python
Dynamic: summary
